{
  "site_id": "wealth",
  "category": "domestic",
  "target_keyword": "令和8年度相続税改正（実需型区分への移動）",
  "h1_title": "2026年版・不動産投資の聖書：バブル崩壊と「大転換（Sea Change）」を生き抜くための戦略書",
  "intro_hook": "冷徹な不動産ストラテジスト（バブル崩壊・リーマンショック経験者）による、2026年の市場転換点において資産防衛および最大化を狙う投資家向けの [IMAGE_1] 不動産投資ガイド。",
  "sections": [
    {
      "h2_heading": "投資判断の基準：3つの「鉄の掟」",
      "content_html": "我々の意思決定は、希望的観測ではなく、以下の冷徹なロジックに基づく。「今回は違う」は禁句、金利の「大転換（Sea Change）」を直視せよ、現金（円）は「ゴミ」だが、流動性は「王」である。 [EXPERT_BOX]"
    },
    {
      "h2_heading": "市場分析の結論：なぜ2026年に東京市場は「逆回転」するのか",
      "content_html": "「変動金利という時限爆弾」と「海外マネーの利回り選別」が2026年に限界を迎えるからだ。パワーカップルの「債務不履行」リスク、海外投資家の「冷徹なエグジット」、「新築プレミアム」の剥落が東京マーケットを直撃する。 [TABLE]"
    },
    {
      "h2_heading": "行動指針（Action Plan）：ボロ船から方舟へ",
      "content_html": "2026年の嵐が来る前に、「郊外・準郊外のマンション・戸建て」「新築タワーマンション」「再開発『期待』だけで上がっているエリア」を即座に売却し、「都心3区の『低層・中古（Vintage）』レジデンス」「ゴールド（金）および『安定通貨国』の不動産」に乗り換えよ。[EXPERT_BOX]"
    }
  ],
  "conclusion": "2026年、生き残った者が勝者となる。[IMAGE_3]",
  "meta_description": "バブル崩壊と「大転換」を生き抜く不動産投資ストラテジー。郊外・新築マンション売却、都心中古物件・ゴールド買い替え等を提案。",
  "manifesto_check": "「新築の輝き（虚飾）を捨て、中古の歴史（本質）を取る」「円という孤島を捨て、世界（外貨）へ打って出る」の2つの基本哲学に沿った内容となっている。"
}